<annotation>
	<folder></folder>
	<filename>LA0335_jpg.rf.277595c5135826efa0b9624a684f3f35.jpg</filename>
	<path>LA0335_jpg.rf.277595c5135826efa0b9624a684f3f35.jpg</path>
	<source>
		<database>roboflow.com</database>
	</source>
	<size>
		<width>640</width>
		<height>640</height>
		<depth>3</depth>
	</size>
	<segmented>0</segmented>
	<object>
		<name>Vehicle</name>
		<pose>Unspecified</pose>
		<truncated>0</truncated>
		<difficult>0</difficult>
		<occluded>0</occluded>
		<bndbox>
			<xmin>312</xmin>
			<xmax>352</xmax>
			<ymin>379</ymin>
			<ymax>422</ymax>
		</bndbox>
	</object>
	<object>
		<name>Vehicle</name>
		<pose>Unspecified</pose>
		<truncated>0</truncated>
		<difficult>0</difficult>
		<occluded>0</occluded>
		<bndbox>
			<xmin>171</xmin>
			<xmax>237</xmax>
			<ymin>275</ymin>
			<ymax>306</ymax>
		</bndbox>
	</object>
	<object>
		<name>AIFV</name>
		<pose>Unspecified</pose>
		<truncated>0</truncated>
		<difficult>0</difficult>
		<occluded>0</occluded>
		<bndbox>
			<xmin>357</xmin>
			<xmax>402</xmax>
			<ymin>51</ymin>
			<ymax>106</ymax>
		</bndbox>
	</object>
	<object>
		<name>MBT</name>
		<pose>Unspecified</pose>
		<truncated>0</truncated>
		<difficult>0</difficult>
		<occluded>0</occluded>
		<bndbox>
			<xmin>154</xmin>
			<xmax>231</xmax>
			<ymin>417</ymin>
			<ymax>474</ymax>
		</bndbox>
	</object>
</annotation>
