<annotation>
	<folder></folder>
	<filename>LA652_jpg.rf.38746aa1573835502d3d02af7ca50cbd.jpg</filename>
	<path>LA652_jpg.rf.38746aa1573835502d3d02af7ca50cbd.jpg</path>
	<source>
		<database>roboflow.com</database>
	</source>
	<size>
		<width>640</width>
		<height>640</height>
		<depth>3</depth>
	</size>
	<segmented>0</segmented>
	<object>
		<name>MBT</name>
		<pose>Unspecified</pose>
		<truncated>0</truncated>
		<difficult>0</difficult>
		<occluded>0</occluded>
		<bndbox>
			<xmin>306</xmin>
			<xmax>332</xmax>
			<ymin>271</ymin>
			<ymax>334</ymax>
		</bndbox>
	</object>
	<object>
		<name>Vehicle</name>
		<pose>Unspecified</pose>
		<truncated>0</truncated>
		<difficult>0</difficult>
		<occluded>0</occluded>
		<bndbox>
			<xmin>246</xmin>
			<xmax>258</xmax>
			<ymin>44</ymin>
			<ymax>71</ymax>
		</bndbox>
	</object>
</annotation>
